itk_elastix_opencl-0.13.0.dist-info/LICENSE
itk_elastix_opencl-0.13.0.dist-info/WHEEL
itk_elastix_opencl-0.13.0.dist-info/top_level.txt
itk_elastix_opencl-0.13.0.dist-info/METADATA
itk_elastix_opencl-0.13.0.dist-info/RECORD
itk/_ElastixPython.so
itk/itkTransformixFilterPython.py
itk/ElastixPython.py
itk/elxParameterObjectPython.py
itk/itkElastixRegistrationMethodPython.py
itk/Configuration/ElastixConfig.py
itk/Configuration/Elastix_snake_case.py
itk_elastix_opencl.libs/libOpenCL-93e30f13.so.1
itk_elastix_opencl.libs/libgomp-7c85b1e2.so.1.0.0
